links_fetcher_robsonfs/__init__.py
links_fetcher_robsonfs/core.py
links_fetcher_robsonfs-0.0.2.dist-info/METADATA
links_fetcher_robsonfs-0.0.2.dist-info/WHEEL
links_fetcher_robsonfs-0.0.2.dist-info/licenses/LICENSE
links_fetcher_robsonfs-0.0.2.dist-info/RECORD
